LICENSE
MANIFEST.in
README.md
setup.py
django_zadmin.egg-info/PKG-INFO
django_zadmin.egg-info/SOURCES.txt
django_zadmin.egg-info/dependency_links.txt
django_zadmin.egg-info/top_level.txt
zadmin/management/commands/copy_templates_and_static.py