Metadata-Version: 1.1
Name: django-zadmin
Version: 0.1.1
Summary: another admin template for django with bootstrap4.0 and sass.
Home-page: http://zadmin.zhaowentao.cn/
Author: steven zhao
Author-email: wentao79@gmail.com
License: MIT License
Platform: UNKNOWN
Classifier: Environment :: Web Environment
Classifier: Framework :: Django
Classifier: Framework :: Django :: 1.9
Classifier: Intended Audience :: Developers
Classifier: License :: OSI Approved :: MIT License
Classifier: Operating System :: OS Independent
Classifier: Programming Language :: Python
Classifier: Programming Language :: Python :: 2.7
Classifier: Topic :: Internet :: WWW/HTTP
Classifier: Topic :: Internet :: WWW/HTTP :: Dynamic Content
